[
    {
        "name": "Tier 1",
        "chest_unopened_img": "/images/items/close.png",
        "chest_opened_img": "/images/items/open.png",
        "overlay_background": "#000000",
        "access_rules": [
            " "
        ],
        "children": [
            {
                "name": "Hub 1-1",
                "chest_unopened_img": "/images/items/close.png",
                "chest_opened_img": "/images/items/open.png",
                "overlay_background": "#000000",
                "access_rules": [
                    " "
                ],
                "sections": [
                    {
                        "name": "Hub 1-1, item 1",
                        "access_rules": [],
                        "visibility_rules": [],
                        "item_count": 1
                    },
                    {
                        "name": "Hub 1-1, item 2",
                        "access_rules": [],
                        "visibility_rules": [],
                        "item_count": 1
                    },
                    {
                        "name": "Hub 1-1, item 3",
                        "access_rules": [],
                        "visibility_rules": [],
                        "item_count": 1
                    },
                    {
                        "name": "Hub 1-1, item 4",
                        "access_rules": [],
                        "visibility_rules": [],
                        "item_count": 1
                    },
                    {
                        "name": "Hub 1-1, item 5",
                        "access_rules": [],
                        "visibility_rules": [],
                        "item_count": 1
                    },
                    {
                        "name": "Hub 1-1, item 6",
                        "access_rules": [],
                        "visibility_rules": [],
                        "item_count": 1
                    },
                    {
                        "name": "Hub 1-1, item 7",
                        "access_rules": [],
                        "visibility_rules": [],
                        "item_count": 1
                    },
                    {
                        "name": "Hub 1-1, item 8",
                        "access_rules": [],
                        "visibility_rules": [],
                        "item_count": 1
                    },
                    {
                        "name": "Hub 1-1, item 9",
                        "access_rules": [],
                        "visibility_rules": [],
                        "item_count": 1
                    },
                    {
                        "name": "Hub 1-1, item 10",
                        "access_rules": [],
                        "visibility_rules": [],
                        "item_count": 1
                    }
                ],
                "map_locations": [
                    {
                        "map": "Tier 1",
                        "x": 1537,
                        "y": 294,
                        "size": 6
                    }
                ]
            },
            {
                "name": "Hub 1-2",
                "chest_unopened_img": "/images/items/close.png",
                "chest_opened_img": "/images/items/open.png",
                "overlay_background": "#000000",
                "access_rules": [
                    " "
                ],
                "sections": [
                    {
                        "name": "Hub 1-2, item 1",
                        "access_rules": [],
                        "visibility_rules": [],
                        "item_count": 1
                    },
                    {
                        "name": "Hub 1-2, item 2",
                        "access_rules": [],
                        "visibility_rules": [],
                        "item_count": 1
                    },
                    {
                        "name": "Hub 1-2, item 3",
                        "access_rules": [],
                        "visibility_rules": [],
                        "item_count": 1
                    },
                    {
                        "name": "Hub 1-2, item 4",
                        "access_rules": [],
                        "visibility_rules": [],
                        "item_count": 1
                    },
                    {
                        "name": "Hub 1-2, item 5",
                        "access_rules": [],
                        "visibility_rules": [],
                        "item_count": 1
                    },
                    {
                        "name": "Hub 1-2, item 6",
                        "access_rules": [],
                        "visibility_rules": [],
                        "item_count": 1
                    },
                    {
                        "name": "Hub 1-2, item 7",
                        "access_rules": [],
                        "visibility_rules": [],
                        "item_count": 1
                    },
                    {
                        "name": "Hub 1-2, item 8",
                        "access_rules": [],
                        "visibility_rules": [],
                        "item_count": 1
                    },
                    {
                        "name": "Hub 1-2, item 9",
                        "access_rules": [],
                        "visibility_rules": [],
                        "item_count": 1
                    },
                    {
                        "name": "Hub 1-2, item 10",
                        "access_rules": [],
                        "visibility_rules": [],
                        "item_count": 1
                    }
                ],
                "map_locations": [
                    {
                        "map": "Tier 1",
                        "x": 452,
                        "y": 614,
                        "size": 6
                    }
                ]
            },
            {
                "name": "Hub 1-3",
                "chest_unopened_img": "/images/items/close.png",
                "chest_opened_img": "/images/items/open.png",
                "overlay_background": "#000000",
                "access_rules": [
                    " "
                ],
                "sections": [
                    {
                        "name": "Hub 1-3, item 1",
                        "access_rules": [],
                        "visibility_rules": [],
                        "item_count": 1
                    },
                    {
                        "name": "Hub 1-3, item 2",
                        "access_rules": [],
                        "visibility_rules": [],
                        "item_count": 1
                    },
                    {
                        "name": "Hub 1-3, item 3",
                        "access_rules": [],
                        "visibility_rules": [],
                        "item_count": 1
                    },
                    {
                        "name": "Hub 1-3, item 4",
                        "access_rules": [],
                        "visibility_rules": [],
                        "item_count": 1
                    },
                    {
                        "name": "Hub 1-3, item 5",
                        "access_rules": [],
                        "visibility_rules": [],
                        "item_count": 1
                    },
                    {
                        "name": "Hub 1-3, item 6",
                        "access_rules": [],
                        "visibility_rules": [],
                        "item_count": 1
                    },
                    {
                        "name": "Hub 1-3, item 7",
                        "access_rules": [],
                        "visibility_rules": [],
                        "item_count": 1
                    },
                    {
                        "name": "Hub 1-3, item 8",
                        "access_rules": [],
                        "visibility_rules": [],
                        "item_count": 1
                    },
                    {
                        "name": "Hub 1-3, item 9",
                        "access_rules": [],
                        "visibility_rules": [],
                        "item_count": 1
                    },
                    {
                        "name": "Hub 1-3, item 10",
                        "access_rules": [],
                        "visibility_rules": [],
                        "item_count": 1
                    }
                ],
                "map_locations": [
                    {
                        "map": "Tier 1",
                        "x": 2306,
                        "y": 86,
                        "size": 6
                    }
                ]
            },
            {
                "name": "Hub 1-4",
                "chest_unopened_img": "/images/items/close.png",
                "chest_opened_img": "/images/items/open.png",
                "overlay_background": "#000000",
                "access_rules": [
                    " "
                ],
                "sections": [
                    {
                        "name": "Hub 1-4, item 1",
                        "access_rules": [],
                        "visibility_rules": [],
                        "item_count": 1
                    },
                    {
                        "name": "Hub 1-4, item 2",
                        "access_rules": [],
                        "visibility_rules": [],
                        "item_count": 1
                    },
                    {
                        "name": "Hub 1-4, item 3",
                        "access_rules": [],
                        "visibility_rules": [],
                        "item_count": 1
                    },
                    {
                        "name": "Hub 1-4, item 4",
                        "access_rules": [],
                        "visibility_rules": [],
                        "item_count": 1
                    },
                    {
                        "name": "Hub 1-4, item 5",
                        "access_rules": [],
                        "visibility_rules": [],
                        "item_count": 1
                    },
                    {
                        "name": "Hub 1-4, item 6",
                        "access_rules": [],
                        "visibility_rules": [],
                        "item_count": 1
                    },
                    {
                        "name": "Hub 1-4, item 7",
                        "access_rules": [],
                        "visibility_rules": [],
                        "item_count": 1
                    },
                    {
                        "name": "Hub 1-4, item 8",
                        "access_rules": [],
                        "visibility_rules": [],
                        "item_count": 1
                    },
                    {
                        "name": "Hub 1-4, item 9",
                        "access_rules": [],
                        "visibility_rules": [],
                        "item_count": 1
                    },
                    {
                        "name": "Hub 1-4, item 10",
                        "access_rules": [],
                        "visibility_rules": [],
                        "item_count": 1
                    }
                ],
                "map_locations": [
                    {
                        "map": "Tier 1",
                        "x": 526,
                        "y": 710,
                        "size": 6
                    }
                ]
            },
            {
                "name": "Hub 1-5",
                "chest_unopened_img": "/images/items/close.png",
                "chest_opened_img": "/images/items/open.png",
                "overlay_background": "#000000",
                "access_rules": [
                    " "
                ],
                "sections": [
                    {
                        "name": "Hub 1-5, item 1",
                        "access_rules": [],
                        "visibility_rules": [],
                        "item_count": 1
                    },
                    {
                        "name": "Hub 1-5, item 2",
                        "access_rules": [],
                        "visibility_rules": [],
                        "item_count": 1
                    },
                    {
                        "name": "Hub 1-5, item 3",
                        "access_rules": [],
                        "visibility_rules": [],
                        "item_count": 1
                    },
                    {
                        "name": "Hub 1-5, item 4",
                        "access_rules": [],
                        "visibility_rules": [],
                        "item_count": 1
                    },
                    {
                        "name": "Hub 1-5, item 5",
                        "access_rules": [],
                        "visibility_rules": [],
                        "item_count": 1
                    },
                    {
                        "name": "Hub 1-5, item 6",
                        "access_rules": [],
                        "visibility_rules": [],
                        "item_count": 1
                    },
                    {
                        "name": "Hub 1-5, item 7",
                        "access_rules": [],
                        "visibility_rules": [],
                        "item_count": 1
                    },
                    {
                        "name": "Hub 1-5, item 8",
                        "access_rules": [],
                        "visibility_rules": [],
                        "item_count": 1
                    },
                    {
                        "name": "Hub 1-5, item 9",
                        "access_rules": [],
                        "visibility_rules": [],
                        "item_count": 1
                    },
                    {
                        "name": "Hub 1-5, item 10",
                        "access_rules": [],
                        "visibility_rules": [],
                        "item_count": 1
                    }
                ],
                "map_locations": [
                    {
                        "map": "Tier 1",
                        "x": 1205,
                        "y": 1441,
                        "size": 6
                    }
                ]
            }
        ]
    }
]